README.md
setup.py
fooltrader/__init__.py
fooltrader/consts.py
fooltrader/items.py
fooltrader/main.py
fooltrader/middlewares.py
fooltrader/pipelines.py
fooltrader/run_spiders.py
fooltrader/settings.py
fooltrader.egg-info/PKG-INFO
fooltrader.egg-info/SOURCES.txt
fooltrader.egg-info/dependency_links.txt
fooltrader.egg-info/entry_points.txt
fooltrader.egg-info/requires.txt
fooltrader.egg-info/top_level.txt
fooltrader/api/__init__.py
fooltrader/api/event.py
fooltrader/api/finance.py
fooltrader/api/quote.py
fooltrader/api/technical.py
fooltrader/connector/__init__.py
fooltrader/connector/es_connector.py
fooltrader/connector/kafka_connector.py
fooltrader/contract/__init__.py
fooltrader/contract/data_contract.py
fooltrader/contract/es_contract.py
fooltrader/contract/files_contract.py
fooltrader/contract/kafka_contract.py
fooltrader/datamanager/__init__.py
fooltrader/datamanager/datamanager.py
fooltrader/datamanager/finance_check.py
fooltrader/datamanager/zipdata.py
fooltrader/datasource/__init__.py
fooltrader/datasource/tdx.py
fooltrader/domain/__init__.py
fooltrader/domain/event.py
fooltrader/domain/finance.py
fooltrader/domain/quote.py
fooltrader/examples/__init__.py
fooltrader/examples/event_trader.py
fooltrader/examples/event_trader1.py
fooltrader/examples/tick_trader.py
fooltrader/examples/time_trader.py
fooltrader/legacy/__init__.py
fooltrader/legacy/legacy.py
fooltrader/proxy/__init__.py
fooltrader/proxy/base_proxy_spider.py
fooltrader/proxy/proxy_manager.py
fooltrader/sched/__init__.py
fooltrader/sched/sched_finance.py
fooltrader/sched/sched_quote.py
fooltrader/spiders/__init__.py
fooltrader/spiders/security_list_spider.py
fooltrader/spiders/stock_finance_report_event_spider.py
fooltrader/spiders/stock_finance_spider.py
fooltrader/spiders/stock_forecast_spider.py
fooltrader/spiders/stock_gn_spider.py
fooltrader/spiders/stock_kdata_spider.py
fooltrader/spiders/stock_kdata_spider_163.py
fooltrader/spiders/stock_kdata_spider_ths.py
fooltrader/spiders/stock_tick_spider.py
fooltrader/spiders/stock_trading_date_spider.py
fooltrader/spiders/future/__init__.py
fooltrader/spiders/future/future_shfe_spider.py
fooltrader/spiders/stock/__init__.py
