Metadata-Version: 1.2
Name: fooltrader
Version: 0.0.1a1
Summary: Open source quantitative framework for Humans
Home-page: https://github.com/foolcage/fooltrader
Author: foolcage
Author-email: 5533061@qq.com
License: UNKNOWN
Project-URL: Bug Reports, https://github.com/foolcage/fooltrader/issues
Project-URL: Funding, https://github.com/foolcage/fooltrader
Project-URL: Say Thanks!, https://saythanks.io/to/foolcage
Project-URL: Source, https://github.com/foolcage/fooltrader
Keywords: stock finance fintech big-data tushare vnpy technical-analysis trading-platform elasticsearch kafka pandas fundamental-analysis quant
Platform: UNKNOWN
Classifier: Development Status :: 3 - Alpha
Classifier: Intended Audience :: Developers
Classifier: Intended Audience :: Customer Service
Classifier: Intended Audience :: Education
Classifier: Intended Audience :: Financial and Insurance Industry
Classifier: Topic :: Software Development :: Build Tools
Classifier: Topic :: Office/Business :: Financial :: Investment
Classifier: License :: OSI Approved :: MIT License
Classifier: Programming Language :: Python :: 3.5
Classifier: Programming Language :: Python :: 3.6
